micropython_h3lis200dl/__init__.py
micropython_h3lis200dl/h3lis200dl.py
micropython_h3lis200dl/i2c_helpers.py
micropython_h3lis200dl-0.1.2.dist-info/LICENSE
micropython_h3lis200dl-0.1.2.dist-info/METADATA
micropython_h3lis200dl-0.1.2.dist-info/WHEEL
micropython_h3lis200dl-0.1.2.dist-info/top_level.txt
micropython_h3lis200dl-0.1.2.dist-info/RECORD
