Metadata-Version: 2.1
Name: micropython-h3lis200dl
Version: 0.1.2
Summary: Micropython Driver for the ST H3LIS200DL Accelerometer
Author-email: JDM <xxyx@mailmeto.mozmail.com>
License: MIT
Project-URL: Homepage, https://github.com/jposada202020/MicroPython_H3LIS200DL
Keywords: sensor,micropython,h3lis200dl,aceleration,Micropython,gravity,accelerometer,H3LIS200DL
Classifier: Intended Audience :: Developers
Classifier: Topic :: Software Development :: Libraries
Classifier: Topic :: Software Development :: Embedded Systems
Classifier: Topic :: System :: Hardware
Classifier: License :: OSI Approved :: MIT License
Classifier: Programming Language :: Python :: Implementation :: MicroPython
License-File: LICENSE
